odoo/addons/l10n_ir_states/README.rst
odoo/addons/l10n_ir_states/__init__.py
odoo/addons/l10n_ir_states/__manifest__.py
odoo/addons/l10n_ir_states/data/res.city.csv
odoo/addons/l10n_ir_states/data/res.country.state.csv
odoo/addons/l10n_ir_states/data/res_country_data.xml
odoo/addons/l10n_ir_states/i18n/fa.po
odoo/addons/l10n_ir_states/i18n/l10n_ir_states.pot
odoo/addons/l10n_ir_states/readme/CONTRIBUTORS.rst
odoo/addons/l10n_ir_states/readme/DESCRIPTION.rst
odoo/addons/l10n_ir_states/readme/USAGE.rst
odoo/addons/l10n_ir_states/static/description/icon.png
odoo/addons/l10n_ir_states/static/description/index.html
odoo14_addon_l10n_ir_states-14.0.3.0.1.dev12.dist-info/METADATA
odoo14_addon_l10n_ir_states-14.0.3.0.1.dev12.dist-info/WHEEL
odoo14_addon_l10n_ir_states-14.0.3.0.1.dev12.dist-info/top_level.txt
odoo14_addon_l10n_ir_states-14.0.3.0.1.dev12.dist-info/RECORD
